goodman_focus/__init__.py
goodman_focus/goodman_focus.py
goodman_focus/version.py
goodman_focus/tests/__init__.py
goodman_focus/tests/test_goodman_focus.py
goodman_focus-2.0.4.dist-info/LICENSE
goodman_focus-2.0.4.dist-info/METADATA
goodman_focus-2.0.4.dist-info/WHEEL
goodman_focus-2.0.4.dist-info/entry_points.txt
goodman_focus-2.0.4.dist-info/top_level.txt
goodman_focus-2.0.4.dist-info/RECORD
