Metadata-Version: 2.1
Name: goodman_focus
Version: 2.0.4
Summary: Finds best focus for Goodman HTS based on a series of images obtained with different focus values
Author-email: Simón Torres <simon.torres@noirlab.edu>
Maintainer-email: Simón Torres <simon.torres@noirlab.edu>
License: BSD 3-Clause License
Project-URL: Homepage, https://soardocs.readthedocs.io/projects/goodmanfocus/en/latest/
Project-URL: Bug Reports, https://github.com/soar-telescope/goodman_focus/issues
Project-URL: Source, https://github.com/soar-telescope/goodman_focus
Keywords: soar,pipelines,astronomy,images,spectroscopy,focus
Classifier: Development Status :: 5 - Production/Stable
Classifier: Environment :: Console
Classifier: Intended Audience :: Developers
Classifier: Intended Audience :: Education
Classifier: Intended Audience :: Science/Research
Classifier: License :: OSI Approved :: BSD License
Classifier: Programming Language :: Python :: 3.8
Classifier: Programming Language :: Python :: 3.9
Classifier: Programming Language :: Python :: 3.10
Classifier: Programming Language :: Python :: 3.11
Classifier: Programming Language :: Python :: 3.12
Classifier: Natural Language :: English
Classifier: Operating System :: POSIX :: Linux
Classifier: Operating System :: POSIX :: Other
Classifier: Operating System :: MacOS :: MacOS X
Classifier: Topic :: Scientific/Engineering :: Astronomy
Classifier: Topic :: Scientific/Engineering :: Information Analysis
Classifier: Topic :: Software Development :: Libraries :: Python Modules
Requires-Python: >=3.8
License-File: LICENSE
Requires-Dist: astropy
Requires-Dist: ccdproc
Requires-Dist: matplotlib
Requires-Dist: numpy
Requires-Dist: packaging
Requires-Dist: pandas
Requires-Dist: scipy
